[{"team_id": 217, "team_name": "Barcelona", "lineup": [{"player_id": 3087, "player_name": "Gn\u00e9gn\u00e9ri Yaya Tour\u00e9", "player_nickname": "Yaya Tour\u00e9", "jersey_number": 24, "country": {"id": 55, "name": "C\u00f4te d'Ivoire"}, "cards": [], "positions": [{"position_id": 10, "position": "Center Defensive Midfield", "from": "00:00", "to": null, "from_period": 1, "to_period": null, "start_reason": "Starting XI", "end_reason": "Final Whistle"}]}, {"player_id": 3672, "player_name": "Zlatan Ibrahimovi\u0107", "player_nickname": null, "jersey_number": 9, "country": {"id": 220, "name": "Sweden"}, "cards": [], "positions": [{"position_id": 23, "position": "Center Forward", "from": "00:00", "to": null, "from_period": 1, "to_period": null, "start_reason": "Starting XI", "end_reason": "Final Whistle"}]}, {"player_id": 3958, "player_name": "Pedro Eliezer Rodr\u00edguez Ledesma", "player_nickname": "Pedro", "jersey_number": 17, "country": {"id": 214, "name": "Spain"}, "cards": [], "positions": []}, {"player_id": 4913, "player_name": "Bojan Krk\u00edc P\u00e9rez", "player_nickname": "Bojan", "jersey_number": 11, "country": {"id": 214, "name": "Spain"}, "cards": [{"time": "77:44", "card_type": "Yellow Card", "reason": "Foul Committed", "period": 2}], "positions": [{"position_id": 21, "position": "Left Wing", "from": "73:21", "to": null, "from_period": 2, "to_period": null, "start_reason": "Substitution - On (Tactical)", "end_reason": "Final Whistle"}]}, {"player_id": 5203, "player_name": "Sergio Busquets i Burgos", "player_nickname": "Sergio Busquets", "jersey_number": 16, "country": {"id": 214, "name": "Spain"}, "cards": [], "positions": []}, {"player_id": 5213, "player_name": "Gerard Piqu\u00e9 Bernab\u00e9u", "player_nickname": "Gerard Piqu\u00e9", "jersey_number": 3, "country": {"id": 214, "name": "Spain"}, "cards": [], "positions": [{"position_id": 3, "position": "Right Center Back", "from": "52:05", "to": null, "from_period": 2, "to_period": null, "start_reason": "Substitution - On (Tactical)", "end_reason": "Final Whistle"}]}, {"player_id": 5503, "player_name": "Lionel Andr\u00e9s Messi Cuccittini", "player_nickname": "Lionel Messi", "jersey_number": 10, "country": {"id": 11, "name": "Argentina"}, "cards": [], "positions": [{"position_id": 17, "position": "Right Wing", "from": "51:35", "to": null, "from_period": 2, "to_period": null, "start_reason": "Substitution - On (Tactical)", "end_reason": "Final Whistle"}]}, {"player_id": 5558, "player_name": "Rafael M\u00e1rquez \u00c1lvarez", "player_nickname": "Rafael M\u00e1rquez", "jersey_number": 4, "country": {"id": 147, "name": "Mexico"}, "cards": [], "positions": [{"position_id": 3, "position": "Right Center Back", "from": "00:00", "to": "52:05", "from_period": 1, "to_period": 2, "start_reason": "Starting XI", "end_reason": "Substitution - Off (Tactical)"}]}, {"player_id": 15516, "player_name": "Thierry Henry", "player_nickname": null, "jersey_number": 14, "country": {"id": 78, "name": "France"}, "cards": [], "positions": [{"position_id": 21, "position": "Left Wing", "from": "00:00", "to": "73:21", "from_period": 1, "to_period": 2, "start_reason": "Starting XI", "end_reason": "Substitution - Off (Tactical)"}]}, {"player_id": 18608, "player_name": "Dmytro Chygrynskiy", "player_nickname": null, "jersey_number": 21, "country": {"id": 238, "name": "Ukraine"}, "cards": [], "positions": [{"position_id": 5, "position": "Left Center Back", "from": "00:00", "to": null, "from_period": 1, "to_period": null, "start_reason": "Starting XI", "end_reason": "Final Whistle"}]}, {"player_id": 20125, "player_name": "Carles Puyol i Saforcada", "player_nickname": "Carles Puyol", "jersey_number": 5, "country": {"id": 214, "name": "Spain"}, "cards": [], "positions": [{"position_id": 2, "position": "Right Back", "from": "00:00", "to": null, "from_period": 1, "to_period": null, "start_reason": "Starting XI", "end_reason": "Final Whistle"}]}, {"player_id": 20131, "player_name": "Xavier Hern\u00e1ndez Creus", "player_nickname": "Xavi", "jersey_number": 6, "country": {"id": 214, "name": "Spain"}, "cards": [], "positions": [{"position_id": 15, "position": "Left Center Midfield", "from": "00:00", "to": null, "from_period": 1, "to_period": null, "start_reason": "Starting XI", "end_reason": "Final Whistle"}]}, {"player_id": 20169, "player_name": "Seydou K\u00e9ita", "player_nickname": "Seydou K\u00e9ita", "jersey_number": 15, "country": {"id": 140, "name": "Mali"}, "cards": [], "positions": [{"position_id": 13, "position": "Right Center Midfield", "from": "00:00", "to": null, "from_period": 1, "to_period": null, "start_reason": "Starting XI", "end_reason": "Final Whistle"}]}, {"player_id": 20176, "player_name": "V\u00edctor Vald\u00e9s Arribas", "player_nickname": "V\u00edctor Vald\u00e9s", "jersey_number": 1, "country": {"id": 214, "name": "Spain"}, "cards": [], "positions": [{"position_id": 1, "position": "Goalkeeper", "from": "00:00", "to": null, "from_period": 1, "to_period": null, "start_reason": "Starting XI", "end_reason": "Final Whistle"}]}, {"player_id": 25919, "player_name": "Gabriel Alejandro Milito", "player_nickname": "Gabriel Milito", "jersey_number": 18, "country": {"id": 11, "name": "Argentina"}, "cards": [], "positions": []}, {"player_id": 26005, "player_name": "Jos\u00e9 Manuel Pinto Colorado", "player_nickname": "Jos\u00e9 Manuel Pinto", "jersey_number": 13, "country": {"id": 214, "name": "Spain"}, "cards": [], "positions": []}, {"player_id": 26613, "player_name": "Maxwell Scherrer Cabelino Andrade", "player_nickname": "Maxwell", "jersey_number": 19, "country": {"id": 31, "name": "Brazil"}, "cards": [], "positions": [{"position_id": 6, "position": "Left Back", "from": "00:00", "to": null, "from_period": 1, "to_period": null, "start_reason": "Starting XI", "end_reason": "Final Whistle"}]}, {"player_id": 26624, "player_name": "Jeffren Isaac Su\u00e1rez Berm\u00fadez", "player_nickname": "Jeffr\u00e9n", "jersey_number": 20, "country": {"id": 246, "name": "Venezuela\u00a0(Bolivarian Republic)"}, "cards": [], "positions": [{"position_id": 17, "position": "Right Wing", "from": "00:00", "to": "51:35", "from_period": 1, "to_period": 2, "start_reason": "Starting XI", "end_reason": "Substitution - Off (Tactical)"}]}]}, {"team_id": 1219, "team_name": "Xerez", "lineup": [{"player_id": 6758, "player_name": "V\u00edctor S\u00e1nchez Mata", "player_nickname": "V\u00edctor S\u00e1nchez", "jersey_number": 14, "country": {"id": 214, "name": "Spain"}, "cards": [{"time": "26:47", "card_type": "Yellow Card", "reason": "Foul Committed", "period": 1}], "positions": [{"position_id": 13, "position": "Right Center Midfield", "from": "00:00", "to": null, "from_period": 1, "to_period": null, "start_reason": "Starting XI", "end_reason": "Final Whistle"}]}, {"player_id": 7105, "player_name": "Fabi\u00e1n Ariel Orellana Valenzuela", "player_nickname": "Fabi\u00e1n Orellana", "jersey_number": 15, "country": {"id": 45, "name": "Chile"}, "cards": [{"time": "71:12", "card_type": "Yellow Card", "reason": "Bad Behaviour", "period": 2}, {"time": "92:03", "card_type": "Red Card", "reason": "Foul Committed", "period": 2}], "positions": [{"position_id": 17, "position": "Right Wing", "from": "00:00", "to": null, "from_period": 1, "to_period": null, "start_reason": "Starting XI", "end_reason": "Final Whistle"}]}, {"player_id": 8440, "player_name": "Aythami Artiles Oliva", "player_nickname": "Aythami Artiles", "jersey_number": 23, "country": {"id": 214, "name": "Spain"}, "cards": [{"time": "15:48", "card_type": "Yellow Card", "reason": "Foul Committed", "period": 1}], "positions": [{"position_id": 3, "position": "Right Center Back", "from": "00:00", "to": "45:00", "from_period": 1, "to_period": 2, "start_reason": "Starting XI", "end_reason": "Substitution - Off (Tactical)"}]}, {"player_id": 26397, "player_name": "Renan Brito Soares", "player_nickname": "Renan", "jersey_number": 13, "country": {"id": 31, "name": "Brazil"}, "cards": [{"time": "82:09", "card_type": "Yellow Card", "reason": "Bad Behaviour", "period": 2}], "positions": [{"position_id": 1, "position": "Goalkeeper", "from": "00:00", "to": null, "from_period": 1, "to_period": null, "start_reason": "Starting XI", "end_reason": "Final Whistle"}]}, {"player_id": 26399, "player_name": "Emilio Jos\u00e9 Viqueira Moure", "player_nickname": "Emilio Viqueira", "jersey_number": 10, "country": {"id": 214, "name": "Spain"}, "cards": [], "positions": []}, {"player_id": 26604, "player_name": "Mat\u00edas Gustavo Alustiza", "player_nickname": null, "jersey_number": 21, "country": {"id": 11, "name": "Argentina"}, "cards": [{"time": "89:29", "card_type": "Red Card", "reason": "Foul Committed", "period": 2}], "positions": [{"position_id": 21, "position": "Left Wing", "from": "78:53", "to": null, "from_period": 2, "to_period": null, "start_reason": "Substitution - On (Tactical)", "end_reason": "Final Whistle"}]}, {"player_id": 26606, "player_name": "Vicente Moreno Peris", "player_nickname": "Vicente Moreno", "jersey_number": 6, "country": {"id": 214, "name": "Spain"}, "cards": [{"time": "87:16", "card_type": "Yellow Card", "reason": "Foul Committed", "period": 2}], "positions": [{"position_id": 15, "position": "Left Center Midfield", "from": "62:27", "to": null, "from_period": 2, "to_period": null, "start_reason": "Substitution - On (Tactical)", "end_reason": "Final Whistle"}]}, {"player_id": 26608, "player_name": "Carlos Calvo Sobrado", "player_nickname": "Carlos Calvo", "jersey_number": 19, "country": {"id": 214, "name": "Spain"}, "cards": [{"time": "90:47", "card_type": "Yellow Card", "reason": "Foul Committed", "period": 2}], "positions": [{"position_id": 3, "position": "Right Center Back", "from": "45:00", "to": "46:15", "from_period": 2, "to_period": 2, "start_reason": "Substitution - On (Tactical)", "end_reason": "Tactical Shift"}, {"position_id": 7, "position": "Right Wing Back", "from": "46:15", "to": null, "from_period": 2, "to_period": null, "start_reason": "Tactical Shift", "end_reason": "Final Whistle"}]}, {"player_id": 26610, "player_name": "Leandro Andr\u00e9s Gioda", "player_nickname": "Leandro Gioda", "jersey_number": 5, "country": {"id": 11, "name": "Argentina"}, "cards": [{"time": "86:40", "card_type": "Yellow Card", "reason": "Bad Behaviour", "period": 2}], "positions": [{"position_id": 4, "position": "Center Back", "from": "00:00", "to": null, "from_period": 1, "to_period": null, "start_reason": "Starting XI", "end_reason": "Final Whistle"}]}, {"player_id": 26611, "player_name": "Emiliano Daniel Armenteros", "player_nickname": "Emiliano Armenteros", "jersey_number": 16, "country": {"id": 11, "name": "Argentina"}, "cards": [], "positions": [{"position_id": 21, "position": "Left Wing", "from": "00:00", "to": "78:53", "from_period": 1, "to_period": 2, "start_reason": "Starting XI", "end_reason": "Substitution - Off (Tactical)"}]}, {"player_id": 26612, "player_name": "Jos\u00e9 Manuel Casado Bizcocho", "player_nickname": "Jos\u00e9 Manuel Casado", "jersey_number": 22, "country": {"id": 214, "name": "Spain"}, "cards": [{"time": "64:49", "card_type": "Yellow Card", "reason": "Bad Behaviour", "period": 2}], "positions": [{"position_id": 8, "position": "Left Wing Back", "from": "00:00", "to": null, "from_period": 1, "to_period": null, "start_reason": "Starting XI", "end_reason": "Final Whistle"}]}, {"player_id": 26614, "player_name": "David Prieto G\u00e1lvez", "player_nickname": "David Prieto", "jersey_number": 18, "country": {"id": 214, "name": "Spain"}, "cards": [], "positions": [{"position_id": 5, "position": "Left Center Back", "from": "00:00", "to": null, "from_period": 1, "to_period": null, "start_reason": "Starting XI", "end_reason": "Final Whistle"}]}, {"player_id": 26615, "player_name": "Francisco Jes\u00fas P\u00e9rez Malia", "player_nickname": "Francis", "jersey_number": 7, "country": {"id": 214, "name": "Spain"}, "cards": [], "positions": [{"position_id": 7, "position": "Right Wing Back", "from": "00:00", "to": "46:15", "from_period": 1, "to_period": 2, "start_reason": "Starting XI", "end_reason": "Tactical Shift"}, {"position_id": 3, "position": "Right Center Back", "from": "46:15", "to": null, "from_period": 2, "to_period": null, "start_reason": "Tactical Shift", "end_reason": "Final Whistle"}]}, {"player_id": 26616, "player_name": "Sidi Yaya Keita", "player_nickname": "Sidi Keita", "jersey_number": 24, "country": {"id": 140, "name": "Mali"}, "cards": [], "positions": [{"position_id": 15, "position": "Left Center Midfield", "from": "00:00", "to": "62:27", "from_period": 1, "to_period": 2, "start_reason": "Starting XI", "end_reason": "Substitution - Off (Tactical)"}]}, {"player_id": 26617, "player_name": "Mario Bermejo Castanedo", "player_nickname": "Mario Bermejo", "jersey_number": 9, "country": {"id": 214, "name": "Spain"}, "cards": [{"time": "82:13", "card_type": "Yellow Card", "reason": "Foul Committed", "period": 2}], "positions": [{"position_id": 23, "position": "Center Forward", "from": "00:00", "to": null, "from_period": 1, "to_period": null, "start_reason": "Starting XI", "end_reason": "Final Whistle"}]}, {"player_id": 147334, "player_name": "Jos\u00e9 Mar\u00eda Gim\u00e9nez P\u00e9rez", "player_nickname": "Chema Gim\u00e9nez", "jersey_number": 1, "country": {"id": 214, "name": "Spain"}, "cards": [], "positions": []}, {"player_id": 147335, "player_name": "Juan Luis Fern\u00e1ndez Redondo", "player_nickname": null, "jersey_number": 2, "country": {"id": 214, "name": "Spain"}, "cards": [], "positions": []}, {"player_id": 147336, "player_name": "Miguel \u00c1ngel Carrilero Gonz\u00e1lez", "player_nickname": "Michel", "jersey_number": 17, "country": {"id": 214, "name": "Spain"}, "cards": [], "positions": []}]}]